pythemo/__init__.py
pythemo/client.py
pythemo/constants.py
pythemo/models.py
pythemo/utils.py
pythemo-0.3.0.dist-info/licenses/LICENSE
pythemo-0.3.0.dist-info/METADATA
pythemo-0.3.0.dist-info/WHEEL
pythemo-0.3.0.dist-info/top_level.txt
pythemo-0.3.0.dist-info/RECORD
