Metadata-Version: 2.4
Name: pythemo
Version: 0.3.0
Summary: A Python client for Themo smart thermostats
Author: Your Name
Author-email: your.email@example.com
License: MIT
License-File: LICENSE
Requires-Dist: httpx
Dynamic: author
Dynamic: author-email
Dynamic: description
Dynamic: description-content-type
Dynamic: license
Dynamic: license-file
Dynamic: requires-dist
Dynamic: summary
